EzyDB_bson/__init__.py
EzyDB_bson/main.py
EzyDB_bson-0.1.0.dist-info/LICENSE
EzyDB_bson-0.1.0.dist-info/METADATA
EzyDB_bson-0.1.0.dist-info/WHEEL
EzyDB_bson-0.1.0.dist-info/entry_points.txt
EzyDB_bson-0.1.0.dist-info/top_level.txt
EzyDB_bson-0.1.0.dist-info/RECORD
