Metadata-Version: 2.1
Name: EzyDB_bson
Version: 0.1.0
Summary: EzyDB-bson is a lightweight, file-based NoSQL database system designed for Python developers. Plugin for EzyDB.
Author: Rakesh Kanna
Author-email: rakeshkanna0108@gmail.com
License: MIT
Keywords: database,db,nosql,bson,storage,store
License-File: LICENSE
Requires-Dist: textPlay
Requires-Dist: EzyDB
Requires-Dist: click
